snakemake_storage_plugin_sftp/__init__.py
snakemake_storage_plugin_sftp/cnopts.py
snakemake_storage_plugin_sftp-0.1.3.dist-info/LICENSE
snakemake_storage_plugin_sftp-0.1.3.dist-info/METADATA
snakemake_storage_plugin_sftp-0.1.3.dist-info/WHEEL
snakemake_storage_plugin_sftp-0.1.3.dist-info/RECORD
